<worksheet xmlns="http://schemas.openxmlformats.org/spreadsheetml/2006/main"><sheetPr><outlinePr summaryBelow="1" summaryRight="1"/><pageSetUpPr/></sheetPr><dimension ref="A1:A41"/><sheetViews><sheetView workbookViewId="0"><selection activeCell="A1" sqref="A1"/></sheetView></sheetViews><sheetFormatPr baseColWidth="8" defaultRowHeight="15"/><cols><col width="118" customWidth="1" min="1" max="1"/></cols><sheetData><row r="1"><c r="A1" s="3" t="inlineStr"><is><t>&#51648;&#50669;&#48324; &#51008;&#54665; &#45908;&#48120;&#45936;&#51060;&#53552; &#49373;&#49457; &#48169;&#48277;&#47200; (&#51204;&#44397; 32,735&#44148;) - v5: Sakasegawa &#44540;&#49324;&#49885; &#51201;&#50857;</t></is></c></row><row r="2"><c r="A2" s="4" t="inlineStr"></c></row><row r="3"><c r="A3" s="5" t="inlineStr"><is><t>[v5 &#54645;&#49900; &#52628;&#44032;&#49324;&#54637;] &#45824;&#44592;&#49884;&#44036;&#51012; &#51221;&#44508;&#48516;&#54252; &#45908;&#48120;&#44050; &#45824;&#49888; Sakasegawa(G/G/c) &#44540;&#49324;&#49885;&#51004;&#47196; &#44228;&#49328;</t></is></c></row><row r="4"><c r="A4" s="4" t="inlineStr"></c></row><row r="5"><c r="A5" s="4" t="inlineStr"><is><t>1) &#52285;&#44396;&#49688;(c) &#49328;&#51221; - &#54788;&#51109;&#44288;&#52272; &#45936;&#51060;&#53552;&#50640;&#49436; &#49892;&#52769;</t></is></c></row><row r="6"><c r="A6" s="4" t="inlineStr"><is><t xml:space="preserve">   &#49436;&#48708;&#49828;&#49884;&#51089;~&#51333;&#47308; &#49884;&#44033;&#51060; &#44217;&#52824;&#45716; &#44396;&#44036;&#51012; &#44228;&#49328;&#54644; "&#46041;&#49884;&#50640; &#49436;&#48708;&#49828; &#51473;&#51064; &#44256;&#44061; &#49688;"&#51032; 90&#54140;&#49468;&#53440;&#51068;&#51012; &#52628;&#51221; &#52285;&#44396;&#49688;&#47196; &#49324;&#50857;:</t></is></c></row><row r="7"><c r="A7" s="4" t="inlineStr"><is><t xml:space="preserve">     &#50864;&#47532;&#51008;&#54665;_&#49324;&#45817;: c=4 (&#44032;&#46041;&#47456; 0.70)  &#54616;&#45208;&#51008;&#54665;_&#51060;&#49688;: c=6 (&#44032;&#46041;&#47456; 0.595)  &#49888;&#54620;&#51008;&#54665;_&#49345;&#46020;: c=7~8 (&#44032;&#46041;&#47456; 0.57)</t></is></c></row><row r="8"><c r="A8" s="4" t="inlineStr"><is><t xml:space="preserve">   &#51060;&#47484; &#50669;&#49328;&#54644; "&#47785;&#54364;&#44032;&#46041;&#47456; &#961;&#8776;0.65" &#44288;&#44228;&#49885;&#51012; &#46020;&#52636;: &#52285;&#44396;&#49688;(c) = ceil( (&#955;/&#956;) / 0.65 ), 1~15&#44060;&#47196; &#51208;&#45800;</t></is></c></row><row r="9"><c r="A9" s="4" t="inlineStr"><is><t xml:space="preserve">   &#51204;&#44397; &#47784;&#46304; &#50689;&#50629;&#51216;&#50640; &#51060; &#44288;&#44228;&#49885;&#51012; &#51201;&#50857;&#54644; &#52285;&#44396;&#49688;&#47484; &#45908;&#48120;&#47196; &#48512;&#50668;</t></is></c></row><row r="10"><c r="A10" s="4" t="inlineStr"></c></row><row r="11"><c r="A11" s="4" t="inlineStr"><is><t>2) ATM &#49436;&#48260;&#49688; = 1 (ATM 1&#45824; = &#49436;&#48260; 1&#44060;&#47196; &#52712;&#44553;, &#49324;&#50857;&#51088; &#51648;&#51221;)</t></is></c></row><row r="12"><c r="A12" s="4" t="inlineStr"></c></row><row r="13"><c r="A13" s="4" t="inlineStr"><is><t>3) Sakasegawa(G/G/c) &#44540;&#49324;&#49885;&#51004;&#47196; &#54217;&#44512; &#45824;&#44592;&#49884;&#44036; Wq &#44228;&#49328;</t></is></c></row><row r="14"><c r="A14" s="4" t="inlineStr"><is><t xml:space="preserve">   &#961; = &#955; / (c&#215;&#956;)</t></is></c></row><row r="15"><c r="A15" s="4" t="inlineStr"><is><t xml:space="preserve">   Wq = [ &#961;^(&#8730;(2(c+1))-1) / (c(1-&#961;)) ] &#215; (CA&#178;+CS&#178;)/2 &#215; (1/&#956;)</t></is></c></row><row r="16"><c r="A16" s="4" t="inlineStr"><is><t xml:space="preserve">   CA&#178; = 1.0 (&#46020;&#52265;&#44036;&#44201; &#48320;&#46041;&#44228;&#49688;&#178;, &#54252;&#50500;&#49569; &#44032;&#51221;)</t></is></c></row><row r="17"><c r="A17" s="4" t="inlineStr"><is><t xml:space="preserve">   CS&#178; = 0.671 (&#49436;&#48708;&#49828;&#49884;&#44036; &#48320;&#46041;&#44228;&#49688;&#178;, &#54788;&#51109;&#44288;&#52272; 3&#44060; &#51648;&#51216; &#49892;&#52769;: &#54364;&#51456;&#54200;&#52264;7.94&#247;&#54217;&#44512;9.69 &#51032; &#51228;&#44273;)</t></is></c></row><row r="18"><c r="A18" s="4" t="inlineStr"><is><t xml:space="preserve">   &#44208;&#44284;&#45716; &#49884;&#44036; &#45800;&#50948;&#47196; &#45208;&#50728; &#46244; &#215;60&#51004;&#47196; &#48516; &#45800;&#50948; &#54872;&#49328;</t></is></c></row><row r="19"><c r="A19" s="4" t="inlineStr"><is><t xml:space="preserve">   &#961;&#44032; 1&#50640; &#44540;&#51217;&#54616;&#47732; &#45824;&#44592;&#49884;&#44036;&#51060; &#48156;&#49328;&#54616;&#48064;&#47196; 0.97&#47196; &#49345;&#54620; &#51208;&#45800;(&#50504;&#51221;&#49457; &#54869;&#48372;)</t></is></c></row><row r="20"><c r="A20" s="4" t="inlineStr"></c></row><row r="21"><c r="A21" s="4" t="inlineStr"><is><t>4) ATM&#46020; &#46041;&#51068;&#54620; Sakasegawa &#49885;&#51012; c=1&#47196; &#51201;&#50857;&#54644; &#45824;&#44592;&#49884;&#44036; &#49328;&#52636;</t></is></c></row><row r="22"><c r="A22" s="4" t="inlineStr"></c></row><row r="23"><c r="A23" s="4" t="inlineStr"><is><t>&#8251; &#44208;&#44284; &#54869;&#51064;: &#52285;&#44396;&#49688;(c)&#47484; &#47785;&#54364;&#44032;&#46041;&#47456; 0.65 &#44592;&#51456;&#51004;&#47196; &#47582;&#52656;&#45480;&#44592; &#46412;&#47928;&#50640;, &#51221;&#49345;&#51201;&#51064; &#44221;&#50864; &#45824;&#44592;&#49884;&#44036;&#51060; &#51687;&#44172;(&#45824;&#48512;&#48516; 1~5&#48516;)</t></is></c></row><row r="24"><c r="A24" s="4" t="inlineStr"><is><t xml:space="preserve">   &#45208;&#50724;&#45716; &#44172; &#51221;&#49345;&#51077;&#45768;&#45796;. &#51060;&#45716; "&#52649;&#48516;&#54620; &#52285;&#44396;&#49688;&#47196; &#50868;&#50689; &#51473;&#51064; &#49345;&#53468;"&#47484; &#44032;&#51221;&#54620; &#44163;&#51060;&#47728;, &#52285;&#44396;&#49688;&#47484; &#51460;&#51060;&#47732;(ITM &#46020;&#51077; &#49884;&#45208;&#47532;&#50724;)</t></is></c></row><row r="25"><c r="A25" s="4" t="inlineStr"><is><t xml:space="preserve">   &#961;&#44032; &#50732;&#46972;&#44032;&#44256; Wq&#46020; &#54632;&#44760; &#44553;&#51613;&#54616;&#45716; &#54805;&#53468;&#47484; &#49884;&#48044;&#47112;&#51060;&#49496;&#50640;&#49436; &#54869;&#51064;&#54624; &#49688; &#51080;&#49845;&#45768;&#45796;.</t></is></c></row><row r="26"><c r="A26" s="4" t="inlineStr"></c></row><row r="27"><c r="A27" s="4" t="inlineStr"><is><t>--- &#51060;&#54616; v4&#44620;&#51648;&#51032; &#45208;&#47672;&#51648; &#47196;&#51649;&#51008; &#46041;&#51068; ---</t></is></c></row><row r="28"><c r="A28" s="4" t="inlineStr"></c></row><row r="29"><c r="A29" s="4" t="inlineStr"><is><t>0) &#54665;&#51221;&#46041; &#47588;&#52845;: &#51452;&#49548; &#54028;&#49905; &#8594; &#51060;&#47492; &#51221;&#54869;&#47588;&#52845; &#8594; &#49707;&#51088;/&#51228; &#51228;&#44144; &#51116;&#47588;&#52845; &#8594; &#47004;&#45924;&#48176;&#51221;(&#51064;&#44396;&#44032;&#51473;) &#49692; (73% &#51060;&#47492;&#44592;&#48152; &#47588;&#52845;)</t></is></c></row><row r="30"><c r="A30" s="4" t="inlineStr"><is><t>1) &#51648;&#51216;&#50976;&#54805;: &#51008;&#54665;&#47749;&#50640; "ATM" &#54252;&#54632; &#8594; ATM&#51204;&#50857;(&#52285;&#44396;&#50630;&#51020;) / &#44536; &#50808; &#8594; &#50689;&#50629;&#51216;(&#52285;&#44396;+ATM)</t></is></c></row><row r="31"><c r="A31" s="4" t="inlineStr"><is><t>2) &#44592;&#48376;&#51060;&#50857;&#47456;(BASE_RATE)=0.6837%, &#44256;&#47161;&#54200;&#54693;(ELDER_BIAS)=2.371 - &#54788;&#51109;&#44288;&#52272; 3&#44060; &#51648;&#51216; &#49892;&#52769; &#52888;&#47532;&#48652;&#47112;&#51060;&#49496;</t></is></c></row><row r="32"><c r="A32" s="4" t="inlineStr"><is><t xml:space="preserve">   &#44256;&#47161;&#48372;&#51221;&#44228;&#49688;(p) = 1 + p&#215;(2.371-1)</t></is></c></row><row r="33"><c r="A33" s="4" t="inlineStr"><is><t>3) &#51068;&#54217;&#44512; &#51060;&#50857;&#44061;(&#52285;&#44396;) = &#54665;&#51221;&#46041;&#51064;&#44396; &#215; 0.6837% &#215; &#44256;&#47161;&#48372;&#51221;&#44228;&#49688; &#215; &#51648;&#51216;&#44508;&#47784;&#51648;&#49688;(&#45908;&#48120;, 0.4~2.5) &#8594; 3~900&#47749; &#51208;&#45800;</t></is></c></row><row r="34"><c r="A34" s="4" t="inlineStr"><is><t xml:space="preserve">   (&#51648;&#51216;&#48324; &#46021;&#47549; &#44228;&#49328; - &#46041; &#51204;&#52404;&#47484; &#51648;&#51216; &#49688;&#47196; &#45208;&#45572;&#51648; &#50506;&#51020;)</t></is></c></row><row r="35"><c r="A35" s="4" t="inlineStr"><is><t>4) &#955;(&#45824;&#54364;) = &#51068;&#54217;&#44512; &#51060;&#50857;&#44061;(&#45824;&#54364;) &#247; 7  (&#50689;&#50629;&#49884;&#44036; 09:00~16:00 &#44032;&#51221;)</t></is></c></row><row r="36"><c r="A36" s="4" t="inlineStr"><is><t>5) &#49436;&#48708;&#49828;&#49884;&#44036;(&#52285;&#44396;) = N(9.69,3.2) &#215; (1+&#44256;&#47161;&#48708;&#50984;&#215;0.35) + &#51648;&#51216;&#44508;&#47784;&#48372;&#51221;, 4~18&#48516; &#51208;&#45800; / ATM = &#44512;&#46321;&#48516;&#54252;(1~2&#48516;)</t></is></c></row><row r="37"><c r="A37" s="4" t="inlineStr"><is><t>6) &#956;(&#45824;&#54364;) = 60 &#247; &#49436;&#48708;&#49828;&#49884;&#44036;(&#45824;&#54364;)</t></is></c></row><row r="38"><c r="A38" s="4" t="inlineStr"><is><t>7) ATM &#51060;&#50857;&#48708;&#50984; = clip(0.5-&#44256;&#47161;&#51064;&#44396;&#48708;&#50984;, 0.20, 0.50)</t></is></c></row><row r="39"><c r="A39" s="4" t="inlineStr"></c></row><row r="40"><c r="A40" s="4" t="inlineStr"><is><t>&#8251; &#54665;&#51221;&#46041; &#51064;&#44396;&#183;&#44256;&#47161;&#51064;&#44396;&#48708;&#50984;&#51008; &#49892;&#52769; &#53685;&#44228;, &#44592;&#48376;&#51060;&#50857;&#47456;&#183;&#44256;&#47161;&#54200;&#54693;&#183;&#52285;&#44396;&#49688;(c) &#44288;&#44228;&#49885;&#183;CS&#178;&#45716; &#54788;&#51109;&#44288;&#52272; &#49892;&#52769; &#52888;&#47532;&#48652;&#47112;&#51060;&#49496;&#44050;,</t></is></c></row><row r="41"><c r="A41" s="4" t="inlineStr"><is><t xml:space="preserve">   &#44060;&#48324; &#51648;&#51216; &#48176;&#48516;(&#51648;&#51216;&#44508;&#47784;&#51648;&#49688;)&#51008; &#49884;&#48044;&#47112;&#51060;&#49496;&#50857; &#45908;&#48120;&#51077;&#45768;&#45796;.</t></is></c></row></sheetData><pageMargins left="0.75" right="0.75" top="1" bottom="1" header="0.5" footer="0.5"/></worksheet>